pyclics/__init__.py
pyclics/__main__.py
pyclics/api.py
pyclics/colexifications.py
pyclics/db.py
pyclics/interfaces.py
pyclics/models.py
pyclics/plugin.py
pyclics/util.py
pyclics/zenodo.py
pyclics/app/clips.css
pyclics/app/d3.v3.js
pyclics/app/favicon.png
pyclics/app/graph.html
pyclics/app/index.html
pyclics/app/jquery-latest.js
pyclics/app/jquery-ui.css
pyclics/app/jquery-ui.js
pyclics/app/our.css
pyclics/app/topojson.js
pyclics/app/visualize.js
pyclics/app/world-110m.json
pyclics/commands/__init__.py
pyclics/commands/cluster.py
pyclics/commands/colexification.py
pyclics/commands/datasets.py
pyclics/commands/datasetspec.py
pyclics/commands/geojson.py
pyclics/commands/graph_stats.py
pyclics/commands/load.py
pyclics/commands/makeapp.py
pyclics/commands/runapp.py
pyclics-3.1.0.dist-info/LICENSE
pyclics-3.1.0.dist-info/METADATA
pyclics-3.1.0.dist-info/WHEEL
pyclics-3.1.0.dist-info/entry_points.txt
pyclics-3.1.0.dist-info/top_level.txt
pyclics-3.1.0.dist-info/RECORD
